{
  "parent": "dimdoors:dimdoors/dark_ostiology",
  "criteria": {
    "spawn": {
      "conditions": {},
      "trigger": "dimdoors:pocket_spawn_point_set"
    }
  },
  "display": {
    "announce_to_chat": true,
    "background": "dimdoors:textures/block/unravelled_fabric.png",
    "description": {
      "translate": "dimdoors.advancement.out_of_time.desc"
    },
    "frame": "task",
    "hidden": false,
    "icon": {
      "item": "minecraft:respawn_anchor"
    },
    "show_toast": true,
    "title": {
      "translate": "dimdoors.advancement.out_of_time"
    }
  },
  "requirements": [
    [
      "spawn"
    ]
  ],
  "sends_telemetry_event": true
}