{
  "criteria": {
    "inventory_changed": {
      "conditions": {
        "items": [
          {
            "items": [
              "minecraft:ender_pearl"
            ]
          }
        ]
      },
      "trigger": "minecraft:inventory_changed"
    }
  },
  "display": {
    "announce_to_chat": true,
    "background": "dimdoors:textures/block/unravelled_fabric.png",
    "description": {
      "translate": "dimdoors.advancement.root.desc"
    },
    "frame": "task",
    "hidden": false,
    "icon": {
      "item": "dimdoors:rift_blade",
      "nbt": "{Damage:0}"
    },
    "show_toast": true,
    "title": {
      "translate": "dimdoors.advancement.root"
    }
  },
  "requirements": [
    [
      "inventory_changed"
    ]
  ],
  "sends_telemetry_event": true
}