{
  "type": "dimdoors:schematic",
  "id": "lab/reception",
  "builder": {
    "type": "dimdoors:lazy_gen_pocket"
  },
  "modifiers": [
    {
      "type": "dimdoors:rift_data",
      "ids": [1],
      "rift_data": "dimdoors:rift_data/pocket_entrance"
    },
    {
      "type": "dimdoors:template",
      "ids": [2],
      "templateId": "dimdoors:lab/right_lab_hallway"
    },
    {
      "type": "dimdoors:rift_data",
      "ids": [3],
      "rift_data": "dimdoors:rift_data/default_dungeon"
    }
  ]
}
